cgtk/CodeGen.py
cgtk/Context.py
cgtk/__init__.py
cgtk/__main__.py
cgtk-0.0.5.dist-info/METADATA
cgtk-0.0.5.dist-info/WHEEL
cgtk-0.0.5.dist-info/top_level.txt
cgtk-0.0.5.dist-info/RECORD
