Metadata-Version: 2.1
Name: cgtk
Version: 0.0.5
Summary: generate code with python in source file comment
Home-page: https://github.com/xchern/cgtk
Author: Xiaosong Chen
Author-email: xiaosong0911@gmail.com
License: MIT
Platform: UNKNOWN
